phi2_mps-0.0.4.dist-info/METADATA
phi2_mps-0.0.4.dist-info/WHEEL
phi2_mps-0.0.4.dist-info/entry_points.txt
phi2_mps/__init__.py
phi2_mps/cli.py
phi2_mps/phi2.py
phi2_mps-0.0.4.dist-info/RECORD
